pymusas/__init__.py
pymusas/base.py
pymusas/config.py
pymusas/file_utils.py
pymusas/lexicon_collection.py
pymusas/pos_mapper.py
pymusas/py.typed
pymusas/rankers/__init__.py
pymusas/rankers/lexical_match.py
pymusas/rankers/lexicon_entry.py
pymusas/rankers/ranking_meta_data.py
pymusas/spacy_api/__init__.py
pymusas/spacy_api/lexicon_collection.py
pymusas/spacy_api/pos_mapper.py
pymusas/spacy_api/rankers.py
pymusas/spacy_api/taggers/__init__.py
pymusas/spacy_api/taggers/hybrid.py
pymusas/spacy_api/taggers/neural.py
pymusas/spacy_api/taggers/rule_based.py
pymusas/spacy_api/taggers/rules.py
pymusas/spacy_api/utils.py
pymusas/taggers/__init__.py
pymusas/taggers/hybrid.py
pymusas/taggers/neural.py
pymusas/taggers/rule_based.py
pymusas/taggers/rules/__init__.py
pymusas/taggers/rules/mwe.py
pymusas/taggers/rules/rule.py
pymusas/taggers/rules/single_word.py
pymusas/taggers/rules/util.py
pymusas/utils.py
pymusas-0.4.0.dist-info/licenses/LICENSE
pymusas-0.4.0.dist-info/WHEEL
pymusas-0.4.0.dist-info/entry_points.txt
pymusas-0.4.0.dist-info/METADATA
pymusas-0.4.0.dist-info/RECORD
