Metadata-Version: 2.4
Name: pymusas
Version: 0.4.0
Summary: PYthon Multilingual Ucrel Semantic Analysis System
Keywords: usas,USAS,UCREL,ucrel,semantics
Author: UCREL Research Centre
Author-email: UCREL Research Centre <ucrel@lancaster.ac.uk>
License-Expression: Apache-2.0
License-File: LICENSE
Classifier: Operating System :: POSIX :: Linux
Classifier: Operating System :: MacOS :: MacOS X
Classifier: Operating System :: Microsoft :: Windows
Classifier: Programming Language :: Python :: 3
Classifier: Programming Language :: Python :: 3.10
Classifier: Programming Language :: Python :: 3.11
Classifier: Programming Language :: Python :: 3.12
Classifier: Programming Language :: Python :: 3.13
Classifier: Programming Language :: Python :: 3.14
Classifier: Topic :: Scientific/Engineering
Classifier: Intended Audience :: Developers
Classifier: Intended Audience :: Science/Research
Requires-Dist: requests>=2.13.0,<3.0
Requires-Dist: spacy>=3.1.4
Requires-Dist: srsly>=2.4.1,<3.0
Requires-Dist: tqdm>=4.50.0,<5.0
Requires-Dist: typer>=0.3.0,<1.0.0
Requires-Dist: torch>=2.2,<3.0 ; extra == 'neural'
Requires-Dist: transformers>=4.0,<5.0 ; extra == 'neural'
Requires-Dist: wsd-torch-models>0.1.1,<1.0 ; extra == 'neural'
Requires-Python: >=3.10, <3.15
Project-URL: Changelog, https://github.com/UCREL/pymusas/blob/main/CHANGELOG.md
Project-URL: Documentation, https://ucrel.github.io/pymusas/api/base
Project-URL: Homepage, https://ucrel.github.io/pymusas/
Project-URL: Issues, https://github.com/UCREL/pymusas/issues
Project-URL: Repository, https://github.com/UCREL/pymusas
Provides-Extra: neural
